{
  "commitMessage": "vault: {{date}}",
  "autoCommitMessage": "vault backup: {{date}}",
  "commitDateFormat": "YYYY-MM-DD HH:mm:ss",
  "autoSaveInterval": 10,
  "autoPushInterval": 15,
  "autoPullInterval": 15,
  "autoPullOnBoot": true,
  "autoCommitOnlyStaged": false,
  "disablePush": false,
  "pullBeforePush": true,
  "disablePopups": false,
  "showErrorNotices": true,
  "disablePopupsForNoChanges": true,
  "listChangedFilesInMessageBody": false,
  "showStatusBar": true,
  "syncMethod": "rebase",
  "mergeStrategy": "theirs",
  "autoBackupAfterFileChange": true,
  "changesBeforeAutoBackup": 1,
  "differentIntervalCommitAndPush": true,
  "refreshSourceControl": true,
  "basePath": "",
  "gitDir": "",
  "showBranchStatusBar": true
}